deephaven/plugin/json/__init__.py
deephaven_plugin_json-0.0.1.dev4.dist-info/LICENSE
deephaven_plugin_json-0.0.1.dev4.dist-info/METADATA
deephaven_plugin_json-0.0.1.dev4.dist-info/WHEEL
deephaven_plugin_json-0.0.1.dev4.dist-info/entry_points.txt
deephaven_plugin_json-0.0.1.dev4.dist-info/top_level.txt
deephaven_plugin_json-0.0.1.dev4.dist-info/RECORD
