Metadata-Version: 2.1
Name: deephaven-plugin-json
Version: 0.0.1.dev4
Summary: Deephaven Plugin for json
Home-page: https://github.com/deephaven/deephaven-plugin-json
Author: Devin Smith
Author-email: devinsmith@deephaven.io
License: UNKNOWN
Project-URL: Source Code, https://github.com/deephaven/deephaven-plugin-json
Project-URL: Bug Tracker, https://github.com/deephaven/deephaven-plugin-json/issues
Keywords: deephaven,plugin,json
Platform: any
Classifier: Programming Language :: Python :: 3
Classifier: License :: OSI Approved :: Apache Software License
Classifier: Operating System :: OS Independent
Classifier: Environment :: Plugins
Classifier: Development Status :: 3 - Alpha
License-File: LICENSE
Requires-Dist: deephaven-plugin
